src/pyxie.py
pyxie_solana-0.1.0.dist-info/LICENSE
pyxie_solana-0.1.0.dist-info/METADATA
pyxie_solana-0.1.0.dist-info/WHEEL
pyxie_solana-0.1.0.dist-info/entry_points.txt
pyxie_solana-0.1.0.dist-info/top_level.txt
pyxie_solana-0.1.0.dist-info/RECORD
